odoo/addons/easy_my_coop_loan/README.rst
odoo/addons/easy_my_coop_loan/__init__.py
odoo/addons/easy_my_coop_loan/__manifest__.py
odoo/addons/easy_my_coop_loan/data/actions.xml
odoo/addons/easy_my_coop_loan/data/ir_cron_data.xml
odoo/addons/easy_my_coop_loan/data/loan_data.xml
odoo/addons/easy_my_coop_loan/data/mail_template_data.xml
odoo/addons/easy_my_coop_loan/demo/coop.xml
odoo/addons/easy_my_coop_loan/i18n/easy_my_coop_loan.pot
odoo/addons/easy_my_coop_loan/models/__init__.py
odoo/addons/easy_my_coop_loan/models/loan_interest_line.py
odoo/addons/easy_my_coop_loan/models/loan_issue.py
odoo/addons/easy_my_coop_loan/models/loan_issue_line.py
odoo/addons/easy_my_coop_loan/models/res_partner.py
odoo/addons/easy_my_coop_loan/readme/CONTRIBUTORS.rst
odoo/addons/easy_my_coop_loan/readme/DESCRIPTION.rst
odoo/addons/easy_my_coop_loan/reports/__init__.py
odoo/addons/easy_my_coop_loan/reports/loan_interest_line_report.py
odoo/addons/easy_my_coop_loan/reports/loan_issue_line_report.xml
odoo/addons/easy_my_coop_loan/reports/loan_reimbursement_report.xml
odoo/addons/easy_my_coop_loan/reports/loan_report.xml
odoo/addons/easy_my_coop_loan/reports/withholding_tax_declaration_report.xml
odoo/addons/easy_my_coop_loan/security/ir.model.access.csv
odoo/addons/easy_my_coop_loan/static/description/index.html
odoo/addons/easy_my_coop_loan/static/src/scss/loan_report.scss
odoo/addons/easy_my_coop_loan/tests/__init__.py
odoo/addons/easy_my_coop_loan/tests/test_emc_loan.py
odoo/addons/easy_my_coop_loan/views/assets.xml
odoo/addons/easy_my_coop_loan/views/loan_interest_lines_view.xml
odoo/addons/easy_my_coop_loan/views/loan_line_view.xml
odoo/addons/easy_my_coop_loan/views/loan_view.xml
odoo/addons/easy_my_coop_loan/views/menus.xml
odoo/addons/easy_my_coop_loan/views/partner_view.xml
odoo/addons/easy_my_coop_loan/wizards/__init__.py
odoo/addons/easy_my_coop_loan/wizards/payment_report_wizard.py
odoo/addons/easy_my_coop_loan/wizards/payment_report_wizard.xml
odoo12_addon_easy_my_coop_loan-12.0.2.0.1.99.dev25.dist-info/METADATA
odoo12_addon_easy_my_coop_loan-12.0.2.0.1.99.dev25.dist-info/WHEEL
odoo12_addon_easy_my_coop_loan-12.0.2.0.1.99.dev25.dist-info/top_level.txt
odoo12_addon_easy_my_coop_loan-12.0.2.0.1.99.dev25.dist-info/RECORD
