Metadata-Version: 2.1
Name: odoo12-addon-easy-my-coop-loan
Version: 12.0.2.0.1.99.dev25
Summary: This module allows to manage the bonds and subordinated loans subscription life cycle.
Home-page: https://coopiteasy.be
Author: Coop IT Easy SCRLfs
License: AGPL-3
Platform: UNKNOWN
Classifier: Programming Language :: Python
Classifier: Framework :: Odoo
Classifier: Framework :: Odoo :: 12.0
Classifier: License :: OSI Approved :: GNU Affero General Public License v3
Requires-Python: >=3.5
Requires-Dist: odoo12-addon-easy-my-coop
Requires-Dist: odoo (<12.1dev,>=12.0a)
